uipath_tools/__init__.py
uipath_tools/uipathorchestratorapi.py
uipath_tools-0.51.dist-info/METADATA
uipath_tools-0.51.dist-info/WHEEL
uipath_tools-0.51.dist-info/top_level.txt
uipath_tools-0.51.dist-info/RECORD
