Metadata-Version: 2.1
Name: uipath-tools
Version: 0.51
Summary: This is a wrapper for the UiPath orchestrator API
Home-page: https://github.com/shazeltion17/uipath_tools
Author: Samuel Ehrlich
Author-email: samuel.ehrlich@fireanalytics.tech
License: MIT
Platform: UNKNOWN
